sysbro/__init__.py
sysbro/cli.py
sysbro/config_parser.py
sysbro/main.py
sysbro/postgres_monitor.py
sysbro/process_monitor.py
sysbro/redis_cleaner.py
tests/__init__.py
tests/test_config_parser.py
tests/test_postgres_monitor.py
tests/test_process_monitor.py
tests/test_redis_cleaner.py
sysbro-0.0.4.dist-info/LICENSE
sysbro-0.0.4.dist-info/METADATA
sysbro-0.0.4.dist-info/WHEEL
sysbro-0.0.4.dist-info/entry_points.txt
sysbro-0.0.4.dist-info/top_level.txt
sysbro-0.0.4.dist-info/RECORD
