Metadata-Version: 2.1
Name: sysbro
Version: 0.0.4
License-File: LICENSE
Requires-Dist: psutil
Requires-Dist: psycopg2-binary
Requires-Dist: redis
Requires-Dist: tqdm
Requires-Dist: click
